{"year":"2016","weeks":[{"type":"season","number":"1","games":[{"day":"Thu","time":"8:40PM","homeTeam":"Denver Broncos","awayTeam":"Carolina Panthers"},{"day":"Sun","time":"1:04PM","homeTeam":"Jacksonville Jaguars","awayTeam":"Green Bay Packers"},{"day":"Sun","time":"1:04PM","homeTeam":"Baltimore Ravens","awayTeam":"Buffalo Bills"},{"day":"Sun","time":"1:05PM","homeTeam":"Kansas City Chiefs","awayTeam":"San Diego Chargers"},{"day":"Sun","time":"1:05PM","homeTeam":"Atlanta Falcons","awayTeam":"Tampa Bay Buccaneers"},{"day":"Sun","time":"1:05PM","homeTeam":"Tennessee Titans","awayTeam":"Minnesota Vikings"},{"day":"Sun","time":"1:05PM","homeTeam":"New Orleans Saints","awayTeam":"Oakland Raiders"},{"day":"Sun","time":"1:05PM","homeTeam":"New York Jets","awayTeam":"Cincinnati Bengals"},{"day":"Sun","time":"1:05PM","homeTeam":"Philadelphia Eagles","awayTeam":"Cleveland Browns"},{"day":"Sun","time":"1:05PM","homeTeam":"Houston Texans","awayTeam":"Chicago Bears"},{"day":"Sun","time":"4:08PM","homeTeam":"Seattle Seahawks","awayTeam":"Miami Dolphins"},{"day":"Sun","time":"4:27PM","homeTeam":"Dallas Cowboys","awayTeam":"New York Giants"},{"day":"Sun","time":"4:27PM","homeTeam":"Indianapolis Colts","awayTeam":"Detroit Lions"},{"day":"Sun","time":"8:30PM","homeTeam":"Arizona Cardinals","awayTeam":"New England Patriots"},{"day":"Mon","time":"7:11PM","homeTeam":"Washington Redskins","awayTeam":"Pittsburgh Steelers"},{"day":"Mon","time":"10:20PM","homeTeam":"San Francisco 49ers","awayTeam":"Los Angeles Rams"}]},{"type":"season","number":"2","games":[{"day":"Thu","time":"8:26PM","homeTeam":"Buffalo Bills","awayTeam":"New York Jets"},{"day":"Sun","time":"1:02PM","homeTeam":"Houston Texans","awayTeam":"Kansas City Chiefs"},{"day":"Sun","time":"1:02PM","homeTeam":"New England Patriots","awayTeam":"Miami Dolphins"},{"day":"Sun","time":"1:02PM","homeTeam":"Detroit Lions","awayTeam":"Tennessee Titans"},{"day":"Sun","time":"1:02PM","homeTeam":"Pittsburgh Steelers","awayTeam":"Cincinnati Bengals"},{"day":"Sun","time":"1:02PM","homeTeam":"Cleveland Browns","awayTeam":"Baltimore Ravens"},{"day":"Sun","time":"1:03PM","homeTeam":"Carolina Panthers","awayTeam":"San Francisco 49ers"},{"day":"Sun","time":"1:03PM","homeTeam":"Washington Redskins","awayTeam":"Dallas Cowboys"},{"day":"Sun","time":"1:03PM","homeTeam":"New York Giants","awayTeam":"New Orleans Saints"},{"day":"Sun","time":"1:05PM","homeTeam":"Arizona Cardinals","awayTeam":"Tampa Bay Buccaneers"},{"day":"Sun","time":"4:08PM","homeTeam":"Los Angeles Rams","awayTeam":"Seattle Seahawks"},{"day":"Sun","time":"4:25PM","homeTeam":"San Diego Chargers","awayTeam":"Jacksonville Jaguars"},{"day":"Sun","time":"4:25PM","homeTeam":"Oakland Raiders","awayTeam":"Atlanta Falcons"},{"day":"Sun","time":"4:25PM","homeTeam":"Denver Broncos","awayTeam":"Indianapolis Colts"},{"day":"Sun","time":"8:32PM","homeTeam":"Minnesota Vikings","awayTeam":"Green Bay Packers"},{"day":"Mon","time":"8:30PM","homeTeam":"Chicago Bears","awayTeam":"Philadelphia Eagles"}]},{"type":"season","number":"3","games":[{"day":"Thu","time":"8:26PM","homeTeam":"New England Patriots","awayTeam":"Houston Texans"},{"day":"Sun","time":"1:02PM","homeTeam":"Cincinnati Bengals","awayTeam":"Denver Broncos"},{"day":"Sun","time":"1:02PM","homeTeam":"Buffalo Bills","awayTeam":"Arizona Cardinals"},{"day":"Sun","time":"1:02PM","homeTeam":"Miami Dolphins","awayTeam":"Cleveland Browns"},{"day":"Sun","time":"1:02PM","homeTeam":"Tennessee Titans","awayTeam":"Oakland Raiders"},{"day":"Sun","time":"1:02PM","homeTeam":"Jacksonville Jaguars","awayTeam":"Baltimore Ravens"},{"day":"Sun","time":"1:02PM","homeTeam":"Carolina Panthers","awayTeam":"Minnesota Vikings"},{"day":"Sun","time":"1:02PM","homeTeam":"Green Bay Packers","awayTeam":"Detroit Lions"},{"day":"Sun","time":"1:02PM","homeTeam":"New York Giants","awayTeam":"Washington Redskins"},{"day":"Sun","time":"4:05PM","homeTeam":"Seattle Seahawks","awayTeam":"San Francisco 49ers"},{"day":"Sun","time":"4:05PM","homeTeam":"Tampa Bay Buccaneers","awayTeam":"Los Angeles Rams"},{"day":"Sun","time":"4:25PM","homeTeam":"Philadelphia Eagles","awayTeam":"Pittsburgh Steelers"},{"day":"Sun","time":"4:25PM","homeTeam":"Indianapolis Colts","awayTeam":"San Diego Chargers"},{"day":"Sun","time":"4:26PM","homeTeam":"Kansas City Chiefs","awayTeam":"New York Jets"},{"day":"Sun","time":"8:31PM","homeTeam":"Dallas Cowboys","awayTeam":"Chicago Bears"},{"day":"Mon","time":"8:30PM","homeTeam":"New Orleans Saints","awayTeam":"Atlanta Falcons"}]},{"type":"season","number":"4","games":[{"day":"Thu","time":"8:26PM","homeTeam":"Cincinnati Bengals","awayTeam":"Miami Dolphins"},{"day":"Sun","time":"9:35AM","homeTeam":"Jacksonville Jaguars","awayTeam":"Indianapolis Colts"},{"day":"Sun","time":"1:00PM","homeTeam":"Chicago Bears","awayTeam":"Detroit Lions"},{"day":"Sun","time":"1:02PM","homeTeam":"Baltimore Ravens","awayTeam":"Oakland Raiders"},{"day":"Sun","time":"1:02PM","homeTeam":"New England Patriots","awayTeam":"Buffalo Bills"},{"day":"Sun","time":"1:02PM","homeTeam":"Houston Texans","awayTeam":"Tennessee Titans"},{"day":"Sun","time":"1:03PM","homeTeam":"New York Jets","awayTeam":"Seattle Seahawks"},{"day":"Sun","time":"1:04PM","homeTeam":"Atlanta Falcons","awayTeam":"Carolina Panthers"},{"day":"Sun","time":"1:05PM","homeTeam":"Washington Redskins","awayTeam":"Cleveland Browns"},{"day":"Sun","time":"4:05PM","homeTeam":"Tampa Bay Buccaneers","awayTeam":"Denver Broncos"},{"day":"Sun","time":"4:25PM","homeTeam":"Arizona Cardinals","awayTeam":"Los Angeles Rams"},{"day":"Sun","time":"4:25PM","homeTeam":"San Francisco 49ers","awayTeam":"Dallas Cowboys"},{"day":"Sun","time":"4:25PM","homeTeam":"San Diego Chargers","awayTeam":"New Orleans Saints"},{"day":"Sun","time":"8:30PM","homeTeam":"Pittsburgh Steelers","awayTeam":"Kansas City Chiefs"},{"day":"Mon","time":"8:35PM","homeTeam":"Minnesota Vikings","awayTeam":"New York Giants"}]},{"type":"season","number":"5","games":[{"day":"Thu","time":"8:27PM","homeTeam":"San Francisco 49ers","awayTeam":"Arizona Cardinals"},{"day":"Sun","time":"1:02PM","homeTeam":"Indianapolis Colts","awayTeam":"Chicago Bears"},{"day":"Sun","time":"1:02PM","homeTeam":"Detroit Lions","awayTeam":"Philadelphia Eagles"},{"day":"Sun","time":"1:02PM","homeTeam":"Pittsburgh Steelers","awayTeam":"New York Jets"},{"day":"Sun","time":"1:02PM","homeTeam":"Miami Dolphins","awayTeam":"Tennessee Titans"},{"day":"Sun","time":"1:02PM","homeTeam":"Cleveland Browns","awayTeam":"New England Patriots"},{"day":"Sun","time":"1:03PM","homeTeam":"Baltimore Ravens","awayTeam":"Washington Redskins"},{"day":"Sun","time":"1:05PM","homeTeam":"Minnesota Vikings","awayTeam":"Houston Texans"},{"day":"Sun","time":"4:05PM","homeTeam":"Denver Broncos","awayTeam":"Atlanta Falcons"},{"day":"Sun","time":"4:25PM","homeTeam":"Oakland Raiders","awayTeam":"San Diego Chargers"},{"day":"Sun","time":"4:25PM","homeTeam":"Dallas Cowboys","awayTeam":"Cincinnati Bengals"},{"day":"Sun","time":"4:25PM","homeTeam":"Los Angeles Rams","awayTeam":"Buffalo Bills"},{"day":"Sun","time":"8:30PM","homeTeam":"Green Bay Packers","awayTeam":"New York Giants"},{"day":"Mon","time":"8:04PM","homeTeam":"Carolina Panthers","awayTeam":"Tampa Bay Buccaneers"}]},{"type":"season","number":"6","games":[{"day":"Thu","time":"8:25PM","homeTeam":"San Diego Chargers","awayTeam":"Denver Broncos"},{"day":"Sun","time":"1:02PM","homeTeam":"Tennessee Titans","awayTeam":"Cleveland Browns"},{"day":"Sun","time":"1:02PM","homeTeam":"New York Giants","awayTeam":"Baltimore Ravens"},{"day":"Sun","time":"1:02PM","homeTeam":"Chicago Bears","awayTeam":"Jacksonville Jaguars"},{"day":"Sun","time":"1:02PM","homeTeam":"Detroit Lions","awayTeam":"Los Angeles Rams"},{"day":"Sun","time":"1:02PM","homeTeam":"Miami Dolphins","awayTeam":"Pittsburgh Steelers"},{"day":"Sun","time":"1:02PM","homeTeam":"New England Patriots","awayTeam":"Cincinnati Bengals"},{"day":"Sun","time":"1:02PM","homeTeam":"Buffalo Bills","awayTeam":"San Francisco 49ers"},{"day":"Sun","time":"1:03PM","homeTeam":"Washington Redskins","awayTeam":"Philadelphia Eagles"},{"day":"Sun","time":"1:03PM","homeTeam":"New Orleans Saints","awayTeam":"Carolina Panthers"},{"day":"Sun","time":"4:05PM","homeTeam":"Oakland Raiders","awayTeam":"Kansas City Chiefs"},{"day":"Sun","time":"4:25PM","homeTeam":"Green Bay Packers","awayTeam":"Dallas Cowboys"},{"day":"Sun","time":"4:26PM","homeTeam":"Seattle Seahawks","awayTeam":"Atlanta Falcons"},{"day":"Sun","time":"8:32PM","homeTeam":"Houston Texans","awayTeam":"Indianapolis Colts"},{"day":"Mon","time":"8:30PM","homeTeam":"Arizona Cardinals","awayTeam":"New York Jets"}]},{"type":"season","number":"7","games":[{"day":"Thu","time":"8:26PM","homeTeam":"Green Bay Packers","awayTeam":"Chicago Bears"},{"day":"Sun","time":"9:31AM","homeTeam":"Los Angeles Rams","awayTeam":"New York Giants"},{"day":"Sun","time":"1:02PM","homeTeam":"Jacksonville Jaguars","awayTeam":"Oakland Raiders"},{"day":"Sun","time":"1:02PM","homeTeam":"Philadelphia Eagles","awayTeam":"Minnesota Vikings"},{"day":"Sun","time":"1:02PM","homeTeam":"Cincinnati Bengals","awayTeam":"Cleveland Browns"},{"day":"Sun","time":"1:02PM","homeTeam":"Miami Dolphins","awayTeam":"Buffalo Bills"},{"day":"Sun","time":"1:02PM","homeTeam":"Detroit Lions","awayTeam":"Washington Redskins"},{"day":"Sun","time":"1:02PM","homeTeam":"Tennessee Titans","awayTeam":"Indianapolis Colts"},{"day":"Sun","time":"1:03PM","homeTeam":"Kansas City Chiefs","awayTeam":"New Orleans Saints"},{"day":"Sun","time":"1:04PM","homeTeam":"New York Jets","awayTeam":"Baltimore Ravens"},{"day":"Sun","time":"4:05PM","homeTeam":"San Francisco 49ers","awayTeam":"Tampa Bay Buccaneers"},{"day":"Sun","time":"4:05PM","homeTeam":"Atlanta Falcons","awayTeam":"San Diego Chargers"},{"day":"Sun","time":"4:25PM","homeTeam":"Pittsburgh Steelers","awayTeam":"New England Patriots"},{"day":"Sun","time":"8:30PM","homeTeam":"Arizona Cardinals","awayTeam":"Seattle Seahawks"},{"day":"Mon","time":"8:30PM","homeTeam":"Denver Broncos","awayTeam":"Houston Texans"}]},{"type":"season","number":"8","games":[{"day":"Thu","time":"8:26PM","homeTeam":"Tennessee Titans","awayTeam":"Jacksonville Jaguars"},{"day":"Sun","time":"8:36AM","homeTeam":"Cincinnati Bengals","awayTeam":"Washington Redskins"},{"day":"Sun","time":"12:47PM","homeTeam":"Carolina Panthers","awayTeam":"Arizona Cardinals"},{"day":"Sun","time":"1:02PM","homeTeam":"Indianapolis Colts","awayTeam":"Kansas City Chiefs"},{"day":"Sun","time":"1:02PM","homeTeam":"Cleveland Browns","awayTeam":"New York Jets"},{"day":"Sun","time":"1:02PM","homeTeam":"Buffalo Bills","awayTeam":"New England Patriots"},{"day":"Sun","time":"1:02PM","homeTeam":"Tampa Bay Buccaneers","awayTeam":"Oakland Raiders"},{"day":"Sun","time":"1:03PM","homeTeam":"New Orleans Saints","awayTeam":"Seattle Seahawks"},{"day":"Sun","time":"1:03PM","homeTeam":"Houston Texans","awayTeam":"Detroit Lions"},{"day":"Sun","time":"4:05PM","homeTeam":"Denver Broncos","awayTeam":"San Diego Chargers"},{"day":"Sun","time":"4:25PM","homeTeam":"Atlanta Falcons","awayTeam":"Green Bay Packers"},{"day":"Sun","time":"8:31PM","homeTeam":"Dallas Cowboys","awayTeam":"Philadelphia Eagles"},{"day":"Mon","time":"8:31PM","homeTeam":"Chicago Bears","awayTeam":"Minnesota Vikings"}]},{"type":"season","number":"9","games":[{"day":"Thu","time":"8:25PM","homeTeam":"Tampa Bay Buccaneers","awayTeam":"Atlanta Falcons"},{"day":"Sun","time":"1:00PM","homeTeam":"Miami Dolphins","awayTeam":"New York Jets"},{"day":"Sun","time":"1:00PM","homeTeam":"Kansas City Chiefs","awayTeam":"Jacksonville Jaguars"},{"day":"Sun","time":"1:00PM","homeTeam":"Baltimore Ravens","awayTeam":"Pittsburgh Steelers"},{"day":"Sun","time":"1:00PM","homeTeam":"New York Giants","awayTeam":"Philadelphia Eagles"},{"day":"Sun","time":"1:00PM","homeTeam":"Minnesota Vikings","awayTeam":"Detroit Lions"},{"day":"Sun","time":"1:00PM","homeTeam":"Cleveland Browns","awayTeam":"Dallas Cowboys"},{"day":"Sun","time":"4:05PM","homeTeam":"San Francisco 49ers","awayTeam":"New Orleans Saints"},{"day":"Sun","time":"4:05PM","homeTeam":"Los Angeles Rams","awayTeam":"Carolina Panthers"},{"day":"Sun","time":"4:25PM","homeTeam":"Green Bay Packers","awayTeam":"Indianapolis Colts"},{"day":"Sun","time":"4:25PM","homeTeam":"San Diego Chargers","awayTeam":"Tennessee Titans"},{"day":"Sun","time":"8:30PM","homeTeam":"Oakland Raiders","awayTeam":"Denver Broncos"},{"day":"Mon","time":"8:30PM","homeTeam":"Seattle Seahawks","awayTeam":"Buffalo Bills"}]},{"type":"season","number":"10","games":[{"day":"Thu","time":"8:25PM","homeTeam":"Baltimore Ravens","awayTeam":"Cleveland Browns"},{"day":"Sun","time":"1:00PM","homeTeam":"Carolina Panthers","awayTeam":"Kansas City Chiefs"},{"day":"Sun","time":"1:00PM","homeTeam":"Tennessee Titans","awayTeam":"Green Bay Packers"},{"day":"Sun","time":"1:00PM","homeTeam":"Washington Redskins","awayTeam":"Minnesota Vikings"},{"day":"Sun","time":"1:00PM","homeTeam":"Jacksonville Jaguars","awayTeam":"Houston Texans"},{"day":"Sun","time":"1:00PM","homeTeam":"Tampa Bay Buccaneers","awayTeam":"Chicago Bears"},{"day":"Sun","time":"1:00PM","homeTeam":"New Orleans Saints","awayTeam":"Denver Broncos"},{"day":"Sun","time":"1:00PM","homeTeam":"New York Jets","awayTeam":"Los Angeles Rams"},{"day":"Sun","time":"1:00PM","homeTeam":"Philadelphia Eagles","awayTeam":"Atlanta Falcons"},{"day":"Sun","time":"4:05PM","homeTeam":"San Diego Chargers","awayTeam":"Miami Dolphins"},{"day":"Sun","time":"4:25PM","homeTeam":"Arizona Cardinals","awayTeam":"San Francisco 49ers"},{"day":"Sun","time":"4:25PM","homeTeam":"Pittsburgh Steelers","awayTeam":"Dallas Cowboys"},{"day":"Sun","time":"8:30PM","homeTeam":"New England Patriots","awayTeam":"Seattle Seahawks"},{"day":"Mon","time":"8:30PM","homeTeam":"New York Giants","awayTeam":"Cincinnati Bengals"}]},{"type":"season","number":"11","games":[{"day":"Thu","time":"8:25PM","homeTeam":"Carolina Panthers","awayTeam":"New Orleans Saints"},{"day":"Sun","time":"1:00PM","homeTeam":"Cincinnati Bengals","awayTeam":"Buffalo Bills"},{"day":"Sun","time":"1:00PM","homeTeam":"Kansas City Chiefs","awayTeam":"Tampa Bay Buccaneers"},{"day":"Sun","time":"1:00PM","homeTeam":"New York Giants","awayTeam":"Chicago Bears"},{"day":"Sun","time":"1:00PM","homeTeam":"Detroit Lions","awayTeam":"Jacksonville Jaguars"},{"day":"Sun","time":"1:00PM","homeTeam":"Minnesota Vikings","awayTeam":"Arizona Cardinals"},{"day":"Sun","time":"1:00PM","homeTeam":"Indianapolis Colts","awayTeam":"Tennessee Titans"},{"day":"Sun","time":"1:00PM","homeTeam":"Dallas Cowboys","awayTeam":"Baltimore Ravens"},{"day":"Sun","time":"1:00PM","homeTeam":"Cleveland Browns","awayTeam":"Pittsburgh Steelers"},{"day":"Sun","time":"4:05PM","homeTeam":"Los Angeles Rams","awayTeam":"Miami Dolphins"},{"day":"Sun","time":"4:25PM","homeTeam":"San Francisco 49ers","awayTeam":"New England Patriots"},{"day":"Sun","time":"4:25PM","homeTeam":"Seattle Seahawks","awayTeam":"Philadelphia Eagles"},{"day":"Sun","time":"8:30PM","homeTeam":"Washington Redskins","awayTeam":"Green Bay Packers"},{"day":"Mon","time":"8:30PM","homeTeam":"Oakland Raiders","awayTeam":"Houston Texans"}]},{"type":"season","number":"12","games":[{"day":"Thu","time":"12:30PM","homeTeam":"Detroit Lions","awayTeam":"Minnesota Vikings"},{"day":"Thu","time":"4:30PM","homeTeam":"Dallas Cowboys","awayTeam":"Washington Redskins"},{"day":"Thu","time":"8:30PM","homeTeam":"Indianapolis Colts","awayTeam":"Pittsburgh Steelers"},{"day":"Sun","time":"1:00PM","homeTeam":"Atlanta Falcons","awayTeam":"Arizona Cardinals"},{"day":"Sun","time":"1:00PM","homeTeam":"Baltimore Ravens","awayTeam":"Cincinnati Bengals"},{"day":"Sun","time":"1:00PM","homeTeam":"Buffalo Bills","awayTeam":"Jacksonville Jaguars"},{"day":"Sun","time":"1:00PM","homeTeam":"Houston Texans","awayTeam":"San Diego Chargers"},{"day":"Sun","time":"1:00PM","homeTeam":"Chicago Bears","awayTeam":"Tennessee Titans"},{"day":"Sun","time":"1:00PM","homeTeam":"New Orleans Saints","awayTeam":"Los Angeles Rams"},{"day":"Sun","time":"1:00PM","homeTeam":"Miami Dolphins","awayTeam":"San Francisco 49ers"},{"day":"Sun","time":"1:00PM","homeTeam":"Cleveland Browns","awayTeam":"New York Giants"},{"day":"Sun","time":"4:05PM","homeTeam":"Tampa Bay Buccaneers","awayTeam":"Seattle Seahawks"},{"day":"Sun","time":"4:25PM","homeTeam":"New York Jets","awayTeam":"New England Patriots"},{"day":"Sun","time":"4:25PM","homeTeam":"Oakland Raiders","awayTeam":"Carolina Panthers"},{"day":"Sun","time":"8:30PM","homeTeam":"Denver Broncos","awayTeam":"Kansas City Chiefs"},{"day":"Mon","time":"8:30PM","homeTeam":"Philadelphia Eagles","awayTeam":"Green Bay Packers"}]},{"type":"season","number":"13","games":[{"day":"Thu","time":"7:25PM","homeTeam":"Minnesota Vikings","awayTeam":"Dallas Cowboys"},{"day":"Sun","time":"1:00PM","homeTeam":"Chicago Bears","awayTeam":"San Francisco 49ers"},{"day":"Sun","time":"1:00PM","homeTeam":"New Orleans Saints","awayTeam":"Detroit Lions"},{"day":"Sun","time":"1:00PM","homeTeam":"Baltimore Ravens","awayTeam":"Miami Dolphins"},{"day":"Sun","time":"1:00PM","homeTeam":"Jacksonville Jaguars","awayTeam":"Denver Broncos"},{"day":"Sun","time":"1:00PM","homeTeam":"Atlanta Falcons","awayTeam":"Kansas City Chiefs"},{"day":"Sun","time":"1:00PM","homeTeam":"Cincinnati Bengals","awayTeam":"Philadelphia Eagles"},{"day":"Sun","time":"1:00PM","homeTeam":"New England Patriots","awayTeam":"Los Angeles Rams"},{"day":"Sun","time":"1:00PM","homeTeam":"Green Bay Packers","awayTeam":"Houston Texans"},{"day":"Sun","time":"4:05PM","homeTeam":"Oakland Raiders","awayTeam":"Buffalo Bills"},{"day":"Sun","time":"4:25PM","homeTeam":"Pittsburgh Steelers","awayTeam":"New York Giants"},{"day":"Sun","time":"4:25PM","homeTeam":"Arizona Cardinals","awayTeam":"Washington Redskins"},{"day":"Sun","time":"4:25PM","homeTeam":"San Diego Chargers","awayTeam":"Tampa Bay Buccaneers"},{"day":"Sun","time":"8:30PM","homeTeam":"Seattle Seahawks","awayTeam":"Carolina Panthers"},{"day":"Mon","time":"8:30PM","homeTeam":"New York Jets","awayTeam":"Indianapolis Colts"}]},{"type":"season","number":"14","games":[{"day":"Thu","time":"8:25PM","homeTeam":"Kansas City Chiefs","awayTeam":"Oakland Raiders"},{"day":"Sun","time":"1:00PM","homeTeam":"Miami Dolphins","awayTeam":"Arizona Cardinals"},{"day":"Sun","time":"1:00PM","homeTeam":"Carolina Panthers","awayTeam":"San Diego Chargers"},{"day":"Sun","time":"1:00PM","homeTeam":"Detroit Lions","awayTeam":"Chicago Bears"},{"day":"Sun","time":"1:00PM","homeTeam":"Tennessee Titans","awayTeam":"Denver Broncos"},{"day":"Sun","time":"1:00PM","homeTeam":"Indianapolis Colts","awayTeam":"Houston Texans"},{"day":"Sun","time":"1:00PM","homeTeam":"Jacksonville Jaguars","awayTeam":"Minnesota Vikings"},{"day":"Sun","time":"1:00PM","homeTeam":"Cleveland Browns","awayTeam":"Cincinnati Bengals"},{"day":"Sun","time":"1:00PM","homeTeam":"Philadelphia Eagles","awayTeam":"Washington Redskins"},{"day":"Sun","time":"1:00PM","homeTeam":"Buffalo Bills","awayTeam":"Pittsburgh Steelers"},{"day":"Sun","time":"4:05PM","homeTeam":"San Francisco 49ers","awayTeam":"New York Jets"},{"day":"Sun","time":"4:25PM","homeTeam":"Tampa Bay Buccaneers","awayTeam":"New Orleans Saints"},{"day":"Sun","time":"4:25PM","homeTeam":"Green Bay Packers","awayTeam":"Seattle Seahawks"},{"day":"Sun","time":"4:25PM","homeTeam":"Los Angeles Rams","awayTeam":"Atlanta Falcons"},{"day":"Sun","time":"8:30PM","homeTeam":"New York Giants","awayTeam":"Dallas Cowboys"},{"day":"Mon","time":"8:30PM","homeTeam":"New England Patriots","awayTeam":"Baltimore Ravens"}]},{"type":"season","number":"15","games":[{"day":"Thu","time":"8:25PM","homeTeam":"Seattle Seahawks","awayTeam":"Los Angeles Rams"},{"day":"Sat","time":"8:25PM","homeTeam":"New York Jets","awayTeam":"Miami Dolphins"},{"day":"Sun","time":"1:00PM","homeTeam":"Kansas City Chiefs","awayTeam":"Tennessee Titans"},{"day":"Sun","time":"1:00PM","homeTeam":"Buffalo Bills","awayTeam":"Cleveland Browns"},{"day":"Sun","time":"1:00PM","homeTeam":"New York Giants","awayTeam":"Detroit Lions"},{"day":"Sun","time":"1:00PM","homeTeam":"Chicago Bears","awayTeam":"Green Bay Packers"},{"day":"Sun","time":"1:00PM","homeTeam":"Minnesota Vikings","awayTeam":"Indianapolis Colts"},{"day":"Sun","time":"1:00PM","homeTeam":"Cincinnati Bengals","awayTeam":"Pittsburgh Steelers"},{"day":"Sun","time":"1:00PM","homeTeam":"Baltimore Ravens","awayTeam":"Philadelphia Eagles"},{"day":"Sun","time":"1:00PM","homeTeam":"Houston Texans","awayTeam":"Jacksonville Jaguars"},{"day":"Sun","time":"4:05PM","homeTeam":"Arizona Cardinals","awayTeam":"New Orleans Saints"},{"day":"Sun","time":"4:05PM","homeTeam":"Atlanta Falcons","awayTeam":"San Francisco 49ers"},{"day":"Sun","time":"4:25PM","homeTeam":"Denver Broncos","awayTeam":"New England Patriots"},{"day":"Sun","time":"4:25PM","homeTeam":"San Diego Chargers","awayTeam":"Oakland Raiders"},{"day":"Sun","time":"8:30PM","homeTeam":"Dallas Cowboys","awayTeam":"Tampa Bay Buccaneers"},{"day":"Mon","time":"8:30PM","homeTeam":"Washington Redskins","awayTeam":"Carolina Panthers"}]},{"type":"season","number":"16","games":[{"day":"Thu","time":"8:25PM","homeTeam":"Philadelphia Eagles","awayTeam":"New York Giants"},{"day":"Sat","time":"1:00PM","homeTeam":"Carolina Panthers","awayTeam":"Atlanta Falcons"},{"day":"Sat","time":"1:00PM","homeTeam":"New England Patriots","awayTeam":"New York Jets"},{"day":"Sat","time":"1:00PM","homeTeam":"Green Bay Packers","awayTeam":"Minnesota Vikings"},{"day":"Sat","time":"1:00PM","homeTeam":"Buffalo Bills","awayTeam":"Miami Dolphins"},{"day":"Sat","time":"1:00PM","homeTeam":"Cleveland Browns","awayTeam":"San Diego Chargers"},{"day":"Sat","time":"1:00PM","homeTeam":"Jacksonville Jaguars","awayTeam":"Tennessee Titans"},{"day":"Sat","time":"1:00PM","homeTeam":"Chicago Bears","awayTeam":"Washington Redskins"},{"day":"Sat","time":"4:05PM","homeTeam":"Oakland Raiders","awayTeam":"Indianapolis Colts"},{"day":"Sat","time":"4:25PM","homeTeam":"Los Angeles Rams","awayTeam":"San Francisco 49ers"},{"day":"Sat","time":"4:25PM","homeTeam":"New Orleans Saints","awayTeam":"Tampa Bay Buccaneers"},{"day":"Sat","time":"4:25PM","homeTeam":"Seattle Seahawks","awayTeam":"Arizona Cardinals"},{"day":"Sat","time":"8:25PM","homeTeam":"Houston Texans","awayTeam":"Cincinnati Bengals"},{"day":"Sun","time":"4:30PM","homeTeam":"Pittsburgh Steelers","awayTeam":"Baltimore Ravens"},{"day":"Sun","time":"8:30PM","homeTeam":"Kansas City Chiefs","awayTeam":"Denver Broncos"},{"day":"Mon","time":"8:30PM","homeTeam":"Dallas Cowboys","awayTeam":"Detroit Lions"}]},{"type":"season","number":"17","games":[{"day":"Sun","time":"1:00PM","homeTeam":"Pittsburgh Steelers","awayTeam":"Cleveland Browns"},{"day":"Sun","time":"1:00PM","homeTeam":"Minnesota Vikings","awayTeam":"Chicago Bears"},{"day":"Sun","time":"1:00PM","homeTeam":"Tennessee Titans","awayTeam":"Houston Texans"},{"day":"Sun","time":"1:00PM","homeTeam":"Indianapolis Colts","awayTeam":"Jacksonville Jaguars"},{"day":"Sun","time":"1:00PM","homeTeam":"Cincinnati Bengals","awayTeam":"Baltimore Ravens"},{"day":"Sun","time":"1:00PM","homeTeam":"Philadelphia Eagles","awayTeam":"Dallas Cowboys"},{"day":"Sun","time":"1:00PM","homeTeam":"Tampa Bay Buccaneers","awayTeam":"Carolina Panthers"},{"day":"Sun","time":"1:00PM","homeTeam":"Miami Dolphins","awayTeam":"New England Patriots"},{"day":"Sun","time":"1:00PM","homeTeam":"New York Jets","awayTeam":"Buffalo Bills"},{"day":"Sun","time":"4:25PM","homeTeam":"Denver Broncos","awayTeam":"Oakland Raiders"},{"day":"Sun","time":"4:25PM","homeTeam":"San Diego Chargers","awayTeam":"Kansas City Chiefs"},{"day":"Sun","time":"4:25PM","homeTeam":"Atlanta Falcons","awayTeam":"New Orleans Saints"},{"day":"Sun","time":"4:25PM","homeTeam":"Washington Redskins","awayTeam":"New York Giants"},{"day":"Sun","time":"4:25PM","homeTeam":"San Francisco 49ers","awayTeam":"Seattle Seahawks"},{"day":"Sun","time":"4:25PM","homeTeam":"Los Angeles Rams","awayTeam":"Arizona Cardinals"},{"day":"Sun","time":"8:30PM","homeTeam":"Detroit Lions","awayTeam":"Green Bay Packers"}]}]}